[
  {
    "date": "2024-12-06",
    "repo_rate": "6.50%",
    "text": "RBI kept repo rate unchanged at 6.50% in December 2024 MPC meeting. Governor Shaktikanta Das continued pause on rate changes citing inflation concerns."
  },
  {
    "date": "2024-10-09",
    "repo_rate": "6.50%",
    "text": "RBI kept repo rate unchanged at 6.50% in October 2024. Changed stance from 'withdrawal of accommodation' to 'neutral'."
  },
  {
    "date": "2024-02-08",
    "repo_rate": "6.50%",
    "text": "RBI maintained repo rate at 6.50% in February 2024. Sixth consecutive pause."
  },
  {
    "date": "2023-04-06",
    "repo_rate": "6.50%",
    "text": "RBI raised repo rate by 25 basis points to 6.50% in April 2023. This was the last rate hike in the tightening cycle."
  },
  {
    "date": "2023-02-08",
    "repo_rate": "6.25%",
    "text": "RBI raised the repo rate to 6.25% in February 2023, a 25 bps hike from 6.00%."
  },
  {
    "date": "2022-12-07",
    "repo_rate": "6.25%",
    "text": "RBI raised repo rate by 35 bps to 6.25% in December 2022."
  },
  {
    "date": "2022-05-04",
    "repo_rate": "4.40%",
    "text": "RBI began tightening cycle with surprise 40 bps hike to 4.40% in May 2022, responding to rising inflation after COVID."
  },
  {
    "date": "2020-05-22",
    "repo_rate": "4.00%",
    "text": "RBI cut repo rate to historic low of 4.00% during COVID-19 pandemic to support the economy."
  },
  {
    "date": "2019-02-07",
    "repo_rate": "6.25%",
    "text": "RBI cut repo rate to 6.25% in February 2019, beginning an easing cycle under Governor Shaktikanta Das."
  },
  {
    "date": "2018-08-01",
    "repo_rate": "6.50%",
    "text": "RBI raised repo rate to 6.50% in August 2018 under Governor Urjit Patel, citing inflation concerns."
  },
  {
    "date": "2016-10-04",
    "repo_rate": "6.25%",
    "text": "RBI cut repo rate to 6.25% in October 2016 under Governor Urjit Patel."
  }
]